.a.py (Python 3.11)
[Code]
    File Name: dg
    Object Name: <module>
    Qualified Name: <module>
    Arg Count: 0
    Pos Only Arg Count: 0
    KW Only Arg Count: 0
    Stack Size: 3
    Flags: 0x00000000
    [Names]
        'os'
        'sys'
        'requests'
        're'
        'random'
        'time'
        'datetime'
        'getpass'
        'system'
        'psl'
        'bs4'
        'BeautifulSoup'
        'sop'
        'concurrent.futures'
        'ThreadPoolExecutor'
        'bsn'
        'idd'
        'logo'
        'main'
        'msg'
        'cpy'
    [Locals+Names]
    [Constants]
        0
        None
        (
            'system'
        )
        (
            'BeautifulSoup'
        )
        (
            'ThreadPoolExecutor'
        )
        'rm -rf filer.txt'
        [Code]
            File Name: dg
            Object Name: logo
            Qualified Name: logo
            Arg Count: 0
            Pos Only Arg Count: 0
            KW Only Arg Count: 0
            Stack Size: 3
            Flags: 0x00000003 (CO_OPTIMIZED | CO_NEWLOCALS)
            [Names]
                'print'
            [Locals+Names]
            [Constants]
                None
                '\x1b[1;32m â–’â–‡â–‡â–‡â–‡â–‡â–‡â–‡   â–’â– â– â– â– â–’   â–‰â– â– â– â– â–‘   â–ˆ                 â–ˆ '
                '\x1b[1;37m â–‰                       â–ˆ            â–ˆ   â–‰         â–‰      â–ˆ                 â–ˆ '
                '\x1b[1;34m â–‰â– â– â– â–            â–ˆâ– â– â– â– â–ˆ   â–‰â– â– â– â–‘      â–ˆ                 â–ˆ '
                '\x1b[1;31m â–‰                       â–ˆ            â–ˆ   â–‰â–€ â–‘           â–ˆ                 â–ˆ '
                '\x1b[1;36m â–‰                       â–ˆ            â–ˆ   â–‰      â–€ â–’     â–ˆ                 â–ˆ '
                '\x1b[1;37m â–‰                       â–ˆ            â–ˆ   â–‰            â–ˆ   â–‘â–„â–„â–„â–„â–„â–„â–‘ '
                '\x1b[1;33mâ•”â•â•â•â•â•â•â•â•â•â•â•â•â•â•â•â•â•â•â•â•â•â•â•â•â•â•â•â•â•â•â•â•â•â•—'
                '\x1b[1;36mâ•‘âž£ \x1b[1;31mCREATED BY   â—ˆâœ™â—ˆ  \x1b[1;31mOWNER FARU  â•‘'
                '\x1b[1;32mâ•‘âž£ \x1b[1;36mFACEBOK      â—ˆâœ™â—ˆ  \x1b[1;36mFARMAN SIDDIQUE â•‘'
                '\x1b[1;37mâ•‘âž£ \x1b[1;37mGITHUB       â—ˆâœ™â—ˆ  \x1b[1;37 H3NRY INXID3  â•‘'
                '\x1b[1;33mâ•‘âž£ \x1b[1;32mSTATUS       â—ˆâœ™â—ˆ  \x1b[1;32mTOOL IS FREE â•‘'
                '\x1b[1;35mâ•‘âž£ \x1b[1;35mFRIEND       â—ˆâœ™â—ˆ  \x1b[1;35mZOHAN        â•‘'
                '\x1b[1;32mâ•‘âž£ \x1b[1;33mGIRLFRIEND   â—ˆâœ™â—ˆ  \x1b[1;33mGADDAR HAI ðŸ’”   â•‘'
                '\x1b[1;37mâ•‘âž£ \x1b[1;32mWHATSAPP.    â—ˆâœ™â—ˆ  \x1b[1;37m60\x1b[1;36m05\x1b[1;32m16\x1b[1;33m73\x1b[1;35m77   â•‘'
                '\x1b[1;37mâ•šâ•â•â•â•â•â•â•â•â•â•â•â•â•â•â•â•â•â•â•â•â•â•â•â•â•â•â•â•â•â•â•â•â•â•'
                '----------------------------------------------------------------'
                '\n\x1b[37;41m\t   Welcome  To  FARU  Brand   Tools   \x1b[0;m'
            [Disassembly]
                0       RESUME                          0
                2       LOAD_GLOBAL                     1: NULL + print
                14      LOAD_CONST                      1: '\x1b[1;32m â–‘â–ˆâ–ˆâ–ˆâ–ˆâ–ˆâ•—â–‘â–ˆâ–ˆâ–ˆâ–ˆâ–ˆâ–ˆâ•—â–‘â–ˆâ–ˆâ–ˆâ•—â–‘â–‘â–ˆâ–ˆâ•—â–‘â–ˆâ–ˆâ–ˆâ–ˆâ–ˆâ•—â–‘â–ˆâ–ˆâ–ˆâ•—â–‘â–‘â–ˆâ–ˆâ•—'
                16      PRECALL                         1
                20      CALL                            1
                30      POP_TOP                         
                32      LOAD_GLOBAL                     1: NULL + print
                44      LOAD_CONST                      2: '\x1b[1;37m â–ˆâ–ˆâ•”â•â•â–ˆâ–ˆâ•—â–ˆâ–ˆâ•”â•â•â–ˆâ–ˆâ•—â–ˆâ–ˆâ–ˆâ–ˆâ•—â–‘â–ˆâ–ˆâ•‘â–ˆâ–ˆâ•”â•â•â–ˆâ–ˆâ•—â–ˆâ–ˆâ–ˆâ–ˆâ•—â–‘â–ˆâ–ˆâ•‘'
                46      PRECALL                         1
                50      CALL                            1
                60      POP_TOP                         
                62      LOAD_GLOBAL                     1: NULL + print
                74      LOAD_CONST                      3: '\x1b[1;34m â–ˆâ–ˆâ–ˆâ–ˆâ–ˆâ–ˆâ–ˆâ•‘â–ˆâ–ˆâ•‘â–‘â–‘â–ˆâ–ˆâ•‘â–ˆâ–ˆâ•”â–ˆâ–ˆâ•—â–ˆâ–ˆâ•‘â–ˆâ–ˆâ–ˆâ–ˆâ–ˆâ–ˆâ–ˆâ•‘â–ˆâ–ˆâ•”â–ˆâ–ˆâ•—â–ˆâ–ˆâ•‘'
                76      PRECALL                         1
                80      CALL                            1
                90      POP_TOP                         
                92      LOAD_GLOBAL                     1: NULL + print
                104     LOAD_CONST                      4: '\x1b[1;31m â–ˆâ–ˆâ•”â•â•â–ˆâ–ˆâ•‘â–ˆâ–ˆâ•‘â–‘â–‘â–ˆâ–ˆâ•‘â–ˆâ–ˆâ•‘â•šâ–ˆâ–ˆâ–ˆâ–ˆâ•‘â–ˆâ–ˆâ•”â•â•â–ˆâ–ˆâ•‘â–ˆâ–ˆâ•‘â•šâ–ˆâ–ˆâ–ˆâ–ˆâ•‘ '
                106     PRECALL                         1
                110     CALL                            1
                120     POP_TOP                         
                122     LOAD_GLOBAL                     1: NULL + print
                134     LOAD_CONST                      5: '\x1b[1;36m â–ˆâ–ˆâ•‘â–‘â–‘â–ˆâ–ˆâ•‘â–ˆâ–ˆâ–ˆâ–ˆâ–ˆâ–ˆâ•”â•â–ˆâ–ˆâ•‘â–‘â•šâ–ˆâ–ˆâ–ˆâ•‘â–ˆâ–ˆâ•‘â–‘â–‘â–ˆâ–ˆâ•‘â–ˆâ–ˆâ•‘â–‘â•šâ–ˆâ–ˆâ–ˆâ•‘'
                136     PRECALL                         1
                140     CALL                            1
                150     POP_TOP                         
                152     LOAD_GLOBAL                     1: NULL + print
                164     LOAD_CONST                      6: '\x1b[1;37m â•šâ•â•â–‘â–‘â•šâ•â•â•šâ•â•â•â•â•â•â–‘â•šâ•â•â–‘â–‘â•šâ•â•â•â•šâ•â•â–‘â–‘â•šâ•â•â•šâ•â•â–‘â–‘â•šâ•â•â•'
                166     PRECALL                         1
                170     CALL                            1
                180     POP_TOP                         
                182     LOAD_GLOBAL                     1: NULL + print
                194     LOAD_CONST                      7: '\x1b[1;33mâ•”â•â•â•â•â•â•â•â•â•â•â•â•â•â•â•â•â•â•â•â•â•â•â•â•â•â•â•â•â•â•â•â•â•â•—'
                196     PRECALL                         1
                200     CALL                            1
                210     POP_TOP                         
                212     LOAD_GLOBAL                     1: NULL + print
                224     LOAD_CONST                      8: '\x1b[1;36mâ•‘âž£ \x1b[1;31mCREATED BY   â—ˆâœ™â—ˆ  \x1b[1;31mOWNER ADNAN  â•‘'
                226     PRECALL                         1
                230     CALL                            1
                240     POP_TOP                         
                242     LOAD_GLOBAL                     1: NULL + print
                254     LOAD_CONST                      9: '\x1b[1;32mâ•‘âž£ \x1b[1;36mFACEBOK      â—ˆâœ™â—ˆ  \x1b[1;36mAMIT RAJPUT  â•‘'
                256     PRECALL                         1
                260     CALL                            1
                270     POP_TOP                         
                272     LOAD_GLOBAL                     1: NULL + print
                284     LOAD_CONST                      10: '\x1b[1;37mâ•‘âž£ \x1b[1;37mGITHUB       â—ˆâœ™â—ˆ  \x1b[1;37madnankhan77  â•‘'
                286     PRECALL                         1
                290     CALL                            1
                300     POP_TOP                         
                302     LOAD_GLOBAL                     1: NULL + print
                314     LOAD_CONST                      11: '\x1b[1;33mâ•‘âž£ \x1b[1;32mSTATUS       â—ˆâœ™â—ˆ  \x1b[1;32mTOOL IS FREE â•‘'
                316     PRECALL                         1
                320     CALL                            1
                330     POP_TOP                         
                332     LOAD_GLOBAL                     1: NULL + print
                344     LOAD_CONST                      12: '\x1b[1;35mâ•‘âž£ \x1b[1;35mFRIEND       â—ˆâœ™â—ˆ  \x1b[1;35mHONEY        â•‘'
                346     PRECALL                         1
                350     CALL                            1
                360     POP_TOP                         
                362     LOAD_GLOBAL                     1: NULL + print
                374     LOAD_CONST                      13: '\x1b[1;32mâ•‘âž£ \x1b[1;33mGIRLFRIEND   â—ˆâœ™â—ˆ  \x1b[1;33mNHI HAI ðŸ’”   â•‘'
                376     PRECALL                         1
                380     CALL                            1
                390     POP_TOP                         
                392     LOAD_GLOBAL                     1: NULL + print
                404     LOAD_CONST                      14: '\x1b[1;37mâ•‘âž£ \x1b[1;32mWHATSAPP.    â—ˆâœ™â—ˆ  \x1b[1;37m60\x1b[1;36m05\x1b[1;32m16\x1b[1;33m73\x1b[1;35m77   â•‘'
                406     PRECALL                         1
                410     CALL                            1
                420     POP_TOP                         
                422     LOAD_GLOBAL                     1: NULL + print
                434     LOAD_CONST                      15: '\x1b[1;37mâ•šâ•â•â•â•â•â•â•â•â•â•â•â•â•â•â•â•â•â•â•â•â•â•â•â•â•â•â•â•â•â•â•â•â•â•'
                436     PRECALL                         1
                440     CALL                            1
                450     POP_TOP                         
                452     LOAD_GLOBAL                     1: NULL + print
                464     LOAD_CONST                      16: '----------------------------------------------------------------'
                466     PRECALL                         1
                470     CALL                            1
                480     POP_TOP                         
                482     LOAD_GLOBAL                     1: NULL + print
                494     LOAD_CONST                      17: '\n\x1b[37;41m\t   Welcome  To  Adnan  Brand   Tools   \x1b[0;m'
                496     PRECALL                         1
                500     CALL                            1
                510     POP_TOP                         
                512     LOAD_CONST                      0: None
                514     RETURN_VALUE                    
        [Code]
            File Name: dg
            Object Name: main
            Qualified Name: main
            Arg Count: 0
            Pos Only Arg Count: 0
            KW Only Arg Count: 0
            Stack Size: 10
            Flags: 0x00000003 (CO_OPTIMIZED | CO_NEWLOCALS)
            [Names]
                'psl'
                'logo'
                'print'
                'input'
                'requests'
                'get'
                'text'
                'os'
                'sys'
                'exit'
                'int'
                'open'
                'read'
                'cpy'
                'readlines'
                'idd'
                'append'
                'bsn'
                'len'
                'submit'
                'msg'
            [Locals+Names]
                'coki'
                'cookies'
                'ch'
                'delay'
                'lnk'
                'lim'
                'hater'
                'filee'
                'fileee'
                'file'
                'crack'
                'mess'
                'sm'
            [Constants]
                None
                'clear'
                '----------------------------------------------------------------'
                '\x1b[1;97m  Paste >>  Cookie Of ID '
                ' [+] Cookies : '
                'cookie'
                'https://mbasic.facebook.com/'
                (
                    'cookies'
                )
                'mbasic_logout_button'
                ' \x1b[1;91mYour Account is on Checkpoint !!! \x1b[1;97m'
                ' \x1b[1;92m Account Logged in Successfully\x1b[1;97m '
                '-------------------------------------------'
                ' [+] Delay : '
                ' [+] Chat/Inbox Link id : '
                ' [+] File Repeat : '
                ' [+] Haters Name : '
                ' [+] File : '
                'r'
                'filer.txt'
                30
                (
                    'max_workers'
                )
                ''
                ' \x1b[1;97m[+] Total messages : %s'
                ' \x1b[1;97mYour Process Started in Background Do Not Turn Off Data'
                '1'
            [Disassembly]
                0       RESUME                          0
                2       LOAD_GLOBAL                     1: NULL + psl
                14      LOAD_CONST                      1: 'clear'
                16      PRECALL                         1
                20      CALL                            1
                30      POP_TOP                         
                32      LOAD_GLOBAL                     3: NULL + logo
                44      PRECALL                         0
                48      CALL                            0
                58      POP_TOP                         
                60      LOAD_GLOBAL                     5: NULL + print
                72      LOAD_CONST                      2: '----------------------------------------------------------------'
                74      PRECALL                         1
                78      CALL                            1
                88      POP_TOP                         
                90      LOAD_GLOBAL                     5: NULL + print
                102     LOAD_CONST                      3: '\x1b[1;97m  Paste >>  Cookie Of ID '
                104     PRECALL                         1
                108     CALL                            1
                118     POP_TOP                         
                120     LOAD_GLOBAL                     5: NULL + print
                132     LOAD_CONST                      2: '----------------------------------------------------------------'
                134     PRECALL                         1
                138     CALL                            1
                148     POP_TOP                         
                150     LOAD_GLOBAL                     7: NULL + input
                162     LOAD_CONST                      4: ' [+] Cookies : '
                164     PRECALL                         1
                168     CALL                            1
                178     STORE_FAST                      0: coki
                180     LOAD_CONST                      5: 'cookie'
                182     LOAD_FAST                       0: coki
                184     BUILD_MAP                       1
                186     STORE_FAST                      1: cookies
                188     LOAD_GLOBAL                     9: NULL + requests
                200     LOAD_ATTR                       5: get
                210     LOAD_CONST                      6: 'https://mbasic.facebook.com/'
                212     LOAD_FAST                       1: cookies
                214     KW_NAMES                        7: ('cookies',)
                216     PRECALL                         2
                220     CALL                            2
                230     STORE_FAST                      2: ch
                232     LOAD_CONST                      8: 'mbasic_logout_button'
                234     LOAD_FAST                       2: ch
                236     LOAD_ATTR                       6: text
                246     CONTAINS_OP                     0 (in)
                248     POP_JUMP_FORWARD_IF_FALSE       1 (to 252)
                250     JUMP_FORWARD                    45 (to 342)
                252     LOAD_GLOBAL                     5: NULL + print
                264     LOAD_CONST                      9: ' \x1b[1;91mYour Account is on Checkpoint !!! \x1b[1;97m'
                266     PRECALL                         1
                270     CALL                            1
                280     POP_TOP                         
                282     LOAD_GLOBAL                     14: os
                294     LOAD_ATTR                       8: sys
                304     LOAD_METHOD                     9: exit
                326     PRECALL                         0
                330     CALL                            0
                340     POP_TOP                         
                342     LOAD_GLOBAL                     5: NULL + print
                354     LOAD_CONST                      10: ' \x1b[1;92m Account Logged in Successfully\x1b[1;97m '
                356     PRECALL                         1
                360     CALL                            1
                370     POP_TOP                         
                372     LOAD_GLOBAL                     5: NULL + print
                384     LOAD_CONST                      11: '-------------------------------------------'
                386     PRECALL                         1
                390     CALL                            1
                400     POP_TOP                         
                402     LOAD_GLOBAL                     21: NULL + int
                414     LOAD_GLOBAL                     7: NULL + input
                426     LOAD_CONST                      12: ' [+] Delay : '
                428     PRECALL                         1
                432     CALL                            1
                442     PRECALL                         1
                446     CALL                            1
                456     STORE_FAST                      3: delay
                458     LOAD_GLOBAL                     5: NULL + print
                470     LOAD_CONST                      11: '-------------------------------------------'
                472     PRECALL                         1
                476     CALL                            1
                486     POP_TOP                         
                488     LOAD_GLOBAL                     7: NULL + input
                500     LOAD_CONST                      13: ' [+] Chat/Inbox Link id : '
                502     PRECALL                         1
                506     CALL                            1
                516     STORE_FAST                      4: lnk
                518     LOAD_GLOBAL                     5: NULL + print
                530     LOAD_CONST                      11: '-------------------------------------------'
                532     PRECALL                         1
                536     CALL                            1
                546     POP_TOP                         
                548     LOAD_GLOBAL                     21: NULL + int
                560     LOAD_GLOBAL                     7: NULL + input
                572     LOAD_CONST                      14: ' [+] File Repeat : '
                574     PRECALL                         1
                578     CALL                            1
                588     PRECALL                         1
                592     CALL                            1
                602     STORE_FAST                      5: lim
                604     LOAD_GLOBAL                     5: NULL + print
                616     LOAD_CONST                      11: '-------------------------------------------'
                618     PRECALL                         1
                622     CALL                            1
                632     POP_TOP                         
                634     LOAD_GLOBAL                     7: NULL + input
                646     LOAD_CONST                      15: ' [+] Haters Name : '
                648     PRECALL                         1
                652     CALL                            1
                662     STORE_FAST                      6: hater
                664     LOAD_GLOBAL                     5: NULL + print
                676     LOAD_CONST                      11: '-------------------------------------------'
                678     PRECALL                         1
                682     CALL                            1
                692     POP_TOP                         
                694     LOAD_GLOBAL                     7: NULL + input
                706     LOAD_CONST                      16: ' [+] File : '
                708     PRECALL                         1
                712     CALL                            1
                722     STORE_FAST                      7: filee
                724     LOAD_GLOBAL                     23: NULL + open
                736     LOAD_FAST                       7: filee
                738     LOAD_CONST                      17: 'r'
                740     PRECALL                         2
                744     CALL                            2
                754     LOAD_METHOD                     12: read
                776     PRECALL                         0
                780     CALL                            0
                790     STORE_FAST                      8: fileee
                792     LOAD_GLOBAL                     27: NULL + cpy
                804     LOAD_FAST                       8: fileee
                806     LOAD_FAST                       5: lim
                808     PRECALL                         2
                812     CALL                            2
                822     POP_TOP                         
                824     LOAD_GLOBAL                     23: NULL + open
                836     LOAD_CONST                      18: 'filer.txt'
                838     LOAD_CONST                      17: 'r'
                840     PRECALL                         2
                844     CALL                            2
                854     LOAD_METHOD                     14: readlines
                876     PRECALL                         0
                880     CALL                            0
                890     STORE_FAST                      9: file
                892     LOAD_GLOBAL                     30: idd
                904     LOAD_METHOD                     16: append
                926     LOAD_FAST                       9: file
                928     PRECALL                         1
                932     CALL                            1
                942     POP_TOP                         
                944     LOAD_GLOBAL                     35: NULL + bsn
                956     LOAD_CONST                      19: 30
                958     KW_NAMES                        20: ('max_workers',)
                960     PRECALL                         1
                964     CALL                            1
                974     BEFORE_WITH                     
                976     STORE_FAST                      10: crack
                978     LOAD_GLOBAL                     1: NULL + psl
                990     LOAD_CONST                      1: 'clear'
                992     PRECALL                         1
                996     CALL                            1
                1006    POP_TOP                         
                1008    LOAD_GLOBAL                     3: NULL + logo
                1020    PRECALL                         0
                1024    CALL                            0
                1034    POP_TOP                         
                1036    LOAD_GLOBAL                     5: NULL + print
                1048    LOAD_CONST                      21: ''
                1050    PRECALL                         1
                1054    CALL                            1
                1064    POP_TOP                         
                1066    LOAD_GLOBAL                     5: NULL + print
                1078    LOAD_CONST                      22: ' \x1b[1;97m[+] Total messages : %s'
                1080    LOAD_GLOBAL                     37: NULL + len
                1092    LOAD_FAST                       9: file
                1094    PRECALL                         1
                1098    CALL                            1
                1108    BINARY_OP                       6 (%)
                1112    PRECALL                         1
                1116    CALL                            1
                1126    POP_TOP                         
                1128    LOAD_GLOBAL                     5: NULL + print
                1140    LOAD_CONST                      23: ' \x1b[1;97mYour Process Started in Background Do Not Turn Off Data'
                1142    PRECALL                         1
                1146    CALL                            1
                1156    POP_TOP                         
                1158    LOAD_GLOBAL                     5: NULL + print
                1170    LOAD_CONST                      11: '-------------------------------------------'
                1172    PRECALL                         1
                1176    CALL                            1
                1186    POP_TOP                         
                1188    LOAD_GLOBAL                     30: idd
                1200    GET_ITER                        
                1202    FOR_ITER                        41 (to 1286)
                1204    STORE_FAST                      11: mess
                1206    LOAD_CONST                      24: '1'
                1208    STORE_FAST                      12: sm
                1210    LOAD_FAST                       12: sm
                1212    LOAD_CONST                      24: '1'
                1214    COMPARE_OP                      2 (==)
                1220    POP_JUMP_FORWARD_IF_FALSE       31 (to 1284)
                1222    LOAD_FAST                       10: crack
                1224    LOAD_METHOD                     19: submit
                1246    LOAD_GLOBAL                     40: msg
                1258    LOAD_FAST                       11: mess
                1260    LOAD_FAST                       0: coki
                1262    LOAD_FAST                       4: lnk
                1264    LOAD_FAST                       3: delay
                1266    LOAD_FAST                       6: hater
                1268    PRECALL                         6
                1272    CALL                            6
                1282    POP_TOP                         
                1284    JUMP_BACKWARD                   42 (to 1202)
                1286    LOAD_GLOBAL                     14: os
                1298    LOAD_ATTR                       8: sys
                1308    LOAD_METHOD                     9: exit
                1330    PRECALL                         0
                1334    CALL                            0
                1344    POP_TOP                         
                1346    LOAD_CONST                      0: None
                1348    LOAD_CONST                      0: None
                1350    LOAD_CONST                      0: None
                1352    PRECALL                         2
                1356    CALL                            2
                1366    POP_TOP                         
                1368    LOAD_CONST                      0: None
                1370    RETURN_VALUE                    
                1372    PUSH_EXC_INFO                   
                1374    WITH_EXCEPT_START               
                1376    POP_JUMP_FORWARD_IF_TRUE        4 (to 1386)
                1378    RERAISE                         2
                1380    COPY                            3
                1382    POP_EXCEPT                      
                1384    RERAISE                         1
                1386    POP_TOP                         
                1388    POP_EXCEPT                      
                1390    POP_TOP                         
                1392    POP_TOP                         
                1394    LOAD_CONST                      0: None
                1396    RETURN_VALUE                    
        [Code]
            File Name: dg
            Object Name: msg
            Qualified Name: msg
            Arg Count: 5
            Pos Only Arg Count: 0
            KW Only Arg Count: 0
            Stack Size: 13
            Flags: 0x00000003 (CO_OPTIMIZED | CO_NEWLOCALS)
            [Names]
                'requests'
                'Session'
                'time'
                'sleep'
                'datetime'
                'now'
                'str'
                'split'
                'date'
                'today'
                'get'
                'text'
                're'
                'search'
                'group'
                'headers'
                'update'
                'sop'
                'find'
                'post'
                'print'
                'exceptions'
                'ConnectionError'
                'Exception'
            [Locals+Names]
                'mess'
                'coki'
                'lnk'
                'delay'
                'hater'
                'ses'
                'msgs'
                'timm'
                'nm'
                'ti'
                'tim'
                'hff'
                'today'
                'year'
                'month'
                'day'
                'cookies'
                'g_url'
                'g_headers'
                'res1'
                'j2'
                'fb_dtsg'
                'csid'
                'tids'
                'rose1'
                'rose'
                'payload'
                'host'
                'post'
                'e'
                'loop'
            [Constants]
                None
                ' '
                '.'
                '-'
                'cookie'
                'https://d.facebook.com/messages/read/?tid='
                'authority'
                'd.facebook.com'
                'accept'
                'text/html,application/xhtml+xml,application/xml;q=0.9,image/avif,image/webp,image/apng,*/*;q=0.8,application/signed-exchange;v=b3;q=0.9'
                'accept-language'
                'en-US,en;q=0.9'
                'cache-control'
                'max-age=0'
                'referer'
                'sec-ch-prefers-color-scheme'
                'light'
                'sec-ch-ua'
                '" Not A;Brand";v="99", "Chromium";v="101"'
                'sec-ch-ua-full-version-list'
                '" Not A;Brand";v="99.0.0.0", "Chromium";v="101.0.4951.40"'
                'sec-ch-ua-mobile'
                '?1'
                'sec-ch-ua-platform'
                '"Android"'
                'sec-ch-ua-platform-version'
                '"11.0.0"'
                'sec-fetch-dest'
                'document'
                'sec-fetch-mode'
                'navigate'
                'sec-fetch-site'
                'same-origin'
                'sec-fetch-user'
                'upgrade-insecure-requests'
                '1'
                'user-agent'
                'Mozilla/5.0 (Linux; Android 11; TECNO CE7j) AppleWebKit/537.36 (KHTML, like Gecko) Chrome/101.0.4951.40 Mobile Safari/537.36'
                (
                    'url'
                    'cookies'
                    'headers'
                )
                'name="jazoest" value="([^"]+)"'
                1
                'name="fb_dtsg" value="([^"]+)"'
                'name="csid" value="([^"]+)"'
                'name="tids" value="([^"]+)"'
                'content-type'
                'application/x-www-form-urlencoded'
                'html.parser'
                'form'
                'post'
                (
                    'method'
                )
                'action'
                'Send'
                'C3'
                ''
                'legacy'
                (
                    'fb_dtsg'
                    'jazoest'
                    'body'
                    'send'
                    'tids'
                    'wwwupp'
                    'platform_xmd'
                    'referrer'
                    'ctype'
                    'cver'
                    'csid'
                )
                'https://d.facebook.com'
                (
                    'url'
                    'data'
                    'cookies'
                )
                ' \x1b[1;97m[+] Time :\x1b[1;92m '
                ' \x1b[1;97m[+] Date :\x1b[1;92m '
                '/'
                ' \x1b[1;97m[+] Haterz : \x1b[1;92m'
                ' \x1b[1;97m[+] Message :\x1b[1;92m '
                '\x1b[1;97m'
                '-------------------------------------------'
                10
            [Disassembly]
                0       RESUME                          0
                2       LOAD_GLOBAL                     1: NULL + requests
                14      LOAD_ATTR                       1: Session
                24      PRECALL                         0
                28      CALL                            0
                38      STORE_FAST                      5: ses
                40      NOP                             
                42      LOAD_FAST                       0: mess
                44      GET_ITER                        
                46      FOR_ITER                        760 (to 1570)
                50      STORE_FAST                      6: msgs
                52      NOP                             
                54      LOAD_GLOBAL                     5: NULL + time
                66      LOAD_ATTR                       3: sleep
                76      LOAD_FAST                       3: delay
                78      PRECALL                         1
                82      CALL                            1
                92      POP_TOP                         
                94      LOAD_GLOBAL                     8: datetime
                106     LOAD_ATTR                       4: datetime
                116     LOAD_METHOD                     5: now
                138     PRECALL                         0
                142     CALL                            0
                152     STORE_FAST                      7: timm
                154     LOAD_GLOBAL                     13: NULL + str
                166     LOAD_FAST                       7: timm
                168     PRECALL                         1
                172     CALL                            1
                182     LOAD_METHOD                     7: split
                204     LOAD_CONST                      1: ' '
                206     PRECALL                         1
                210     CALL                            1
                220     UNPACK_SEQUENCE                 2
                224     STORE_FAST                      8: nm
                226     STORE_FAST                      9: ti
                228     LOAD_FAST                       9: ti
                230     LOAD_METHOD                     7: split
                252     LOAD_CONST                      2: '.'
                254     PRECALL                         1
                258     CALL                            1
                268     UNPACK_SEQUENCE                 2
                272     STORE_FAST                      10: tim
                274     STORE_FAST                      11: hff
                276     LOAD_GLOBAL                     8: datetime
                288     LOAD_ATTR                       8: date
                298     LOAD_METHOD                     9: today
                320     PRECALL                         0
                324     CALL                            0
                334     STORE_FAST                      12: today
                336     LOAD_GLOBAL                     13: NULL + str
                348     LOAD_FAST                       12: today
                350     PRECALL                         1
                354     CALL                            1
                364     LOAD_METHOD                     7: split
                386     LOAD_CONST                      3: '-'
                388     PRECALL                         1
                392     CALL                            1
                402     UNPACK_SEQUENCE                 3
                406     STORE_FAST                      13: year
                408     STORE_FAST                      14: month
                410     STORE_FAST                      15: day
                412     LOAD_CONST                      4: 'cookie'
                414     LOAD_FAST                       1: coki
                416     BUILD_MAP                       1
                418     STORE_FAST                      16: cookies
                420     LOAD_CONST                      5: 'https://d.facebook.com/messages/read/?tid='
                422     LOAD_FAST                       2: lnk
                424     BINARY_OP                       0 (+)
                428     STORE_FAST                      17: g_url
                430     BUILD_MAP                       0
                432     LOAD_CONST                      6: 'authority'
                434     LOAD_CONST                      7: 'd.facebook.com'
                436     MAP_ADD                         1
                438     LOAD_CONST                      8: 'accept'
                440     LOAD_CONST                      9: 'text/html,application/xhtml+xml,application/xml;q=0.9,image/avif,image/webp,image/apng,*/*;q=0.8,application/signed-exchange;v=b3;q=0.9'
                442     MAP_ADD                         1
                444     LOAD_CONST                      10: 'accept-language'
                446     LOAD_CONST                      11: 'en-US,en;q=0.9'
                448     MAP_ADD                         1
                450     LOAD_CONST                      12: 'cache-control'
                452     LOAD_CONST                      13: 'max-age=0'
                454     MAP_ADD                         1
                456     LOAD_CONST                      14: 'referer'
                458     LOAD_CONST                      5: 'https://d.facebook.com/messages/read/?tid='
                460     LOAD_FAST                       2: lnk
                462     BINARY_OP                       0 (+)
                466     MAP_ADD                         1
                468     LOAD_CONST                      15: 'sec-ch-prefers-color-scheme'
                470     LOAD_CONST                      16: 'light'
                472     MAP_ADD                         1
                474     LOAD_CONST                      17: 'sec-ch-ua'
                476     LOAD_CONST                      18: '" Not A;Brand";v="99", "Chromium";v="101"'
                478     MAP_ADD                         1
                480     LOAD_CONST                      19: 'sec-ch-ua-full-version-list'
                482     LOAD_CONST                      20: '" Not A;Brand";v="99.0.0.0", "Chromium";v="101.0.4951.40"'
                484     MAP_ADD                         1
                486     LOAD_CONST                      21: 'sec-ch-ua-mobile'
                488     LOAD_CONST                      22: '?1'
                490     MAP_ADD                         1
                492     LOAD_CONST                      23: 'sec-ch-ua-platform'
                494     LOAD_CONST                      24: '"Android"'
                496     MAP_ADD                         1
                498     LOAD_CONST                      25: 'sec-ch-ua-platform-version'
                500     LOAD_CONST                      26: '"11.0.0"'
                502     MAP_ADD                         1
                504     LOAD_CONST                      27: 'sec-fetch-dest'
                506     LOAD_CONST                      28: 'document'
                508     MAP_ADD                         1
                510     LOAD_CONST                      29: 'sec-fetch-mode'
                512     LOAD_CONST                      30: 'navigate'
                514     MAP_ADD                         1
                516     LOAD_CONST                      31: 'sec-fetch-site'
                518     LOAD_CONST                      32: 'same-origin'
                520     MAP_ADD                         1
                522     LOAD_CONST                      33: 'sec-fetch-user'
                524     LOAD_CONST                      22: '?1'
                526     MAP_ADD                         1
                528     LOAD_CONST                      34: 'upgrade-insecure-requests'
                530     LOAD_CONST                      35: '1'
                532     MAP_ADD                         1
                534     LOAD_CONST                      36: 'user-agent'
                536     LOAD_CONST                      37: 'Mozilla/5.0 (Linux; Android 11; TECNO CE7j) AppleWebKit/537.36 (KHTML, like Gecko) Chrome/101.0.4951.40 Mobile Safari/537.36'
                538     MAP_ADD                         1
                540     STORE_FAST                      18: g_headers
                542     LOAD_GLOBAL                     1: NULL + requests
                554     LOAD_ATTR                       10: get
                564     LOAD_FAST                       17: g_url
                566     LOAD_FAST                       16: cookies
                568     LOAD_FAST                       18: g_headers
                570     KW_NAMES                        38: ('url', 'cookies', 'headers')
                572     PRECALL                         3
                576     CALL                            3
                586     LOAD_ATTR                       11: text
                596     STORE_FAST                      19: res1
                598     LOAD_GLOBAL                     25: NULL + re
                610     LOAD_ATTR                       13: search
                620     LOAD_CONST                      39: 'name="jazoest" value="([^"]+)"'
                622     LOAD_FAST                       19: res1
                624     PRECALL                         2
                628     CALL                            2
                638     LOAD_METHOD                     14: group
                660     LOAD_CONST                      40: 1
                662     PRECALL                         1
                666     CALL                            1
                676     STORE_FAST                      20: j2
                678     LOAD_GLOBAL                     25: NULL + re
                690     LOAD_ATTR                       13: search
                700     LOAD_CONST                      41: 'name="fb_dtsg" value="([^"]+)"'
                702     LOAD_FAST                       19: res1
                704     PRECALL                         2
                708     CALL                            2
                718     LOAD_METHOD                     14: group
                740     LOAD_CONST                      40: 1
                742     PRECALL                         1
                746     CALL                            1
                756     STORE_FAST                      21: fb_dtsg
                758     LOAD_GLOBAL                     25: NULL + re
                770     LOAD_ATTR                       13: search
                780     LOAD_CONST                      42: 'name="csid" value="([^"]+)"'
                782     LOAD_FAST                       19: res1
                784     PRECALL                         2
                788     CALL                            2
                798     LOAD_METHOD                     14: group
                820     LOAD_CONST                      40: 1
                822     PRECALL                         1
                826     CALL                            1
                836     STORE_FAST                      22: csid
                838     LOAD_GLOBAL                     25: NULL + re
                850     LOAD_ATTR                       13: search
                860     LOAD_CONST                      43: 'name="tids" value="([^"]+)"'
                862     LOAD_FAST                       19: res1
                864     PRECALL                         2
                868     CALL                            2
                878     LOAD_METHOD                     14: group
                900     LOAD_CONST                      40: 1
                902     PRECALL                         1
                906     CALL                            1
                916     STORE_FAST                      23: tids
                918     LOAD_FAST                       5: ses
                920     LOAD_ATTR                       15: headers
                930     LOAD_METHOD                     16: update
                952     LOAD_CONST                      44: 'content-type'
                954     LOAD_CONST                      45: 'application/x-www-form-urlencoded'
                956     BUILD_MAP                       1
                958     PRECALL                         1
                962     CALL                            1
                972     POP_TOP                         
                974     LOAD_GLOBAL                     35: NULL + sop
                986     LOAD_FAST                       19: res1
                988     LOAD_CONST                      46: 'html.parser'
                990     PRECALL                         2
                994     CALL                            2
                1004    STORE_FAST                      24: rose1
                1006    LOAD_FAST                       24: rose1
                1008    LOAD_METHOD                     18: find
                1030    LOAD_CONST                      47: 'form'
                1032    LOAD_CONST                      48: 'post'
                1034    KW_NAMES                        49: ('method',)
                1036    PRECALL                         2
                1040    CALL                            2
                1050    LOAD_CONST                      50: 'action'
                1052    BINARY_SUBSCR                   
                1062    STORE_FAST                      25: rose
                1064    LOAD_FAST                       21: fb_dtsg
                1066    LOAD_FAST                       20: j2
                1068    LOAD_FAST                       4: hater
                1070    LOAD_CONST                      1: ' '
                1072    BINARY_OP                       0 (+)
                1076    LOAD_GLOBAL                     13: NULL + str
                1088    LOAD_FAST                       6: msgs
                1090    PRECALL                         1
                1094    CALL                            1
                1104    BINARY_OP                       0 (+)
                1108    LOAD_CONST                      51: 'Send'
                1110    LOAD_FAST                       23: tids
                1112    LOAD_CONST                      52: 'C3'
                1114    LOAD_CONST                      53: ''
                1116    LOAD_CONST                      53: ''
                1118    LOAD_CONST                      53: ''
                1120    LOAD_CONST                      54: 'legacy'
                1122    LOAD_FAST                       22: csid
                1124    LOAD_CONST                      55: ('fb_dtsg', 'jazoest', 'body', 'send', 'tids', 'wwwupp', 'platform_xmd', 'referrer', 'ctype', 'cver', 'csid')
                1126    BUILD_CONST_KEY_MAP             11
                1128    STORE_FAST                      26: payload
                1130    LOAD_CONST                      56: 'https://d.facebook.com'
                1132    STORE_FAST                      27: host
                1134    LOAD_FAST                       5: ses
                1136    LOAD_METHOD                     19: post
                1158    LOAD_FAST                       27: host
                1160    LOAD_FAST                       25: rose
                1162    BINARY_OP                       0 (+)
                1166    LOAD_FAST                       26: payload
                1168    LOAD_FAST                       16: cookies
                1170    KW_NAMES                        57: ('url', 'data', 'cookies')
                1172    PRECALL                         3
                1176    CALL                            3
                1186    LOAD_ATTR                       11: text
                1196    STORE_FAST                      28: post
                1198    LOAD_GLOBAL                     41: NULL + print
                1210    LOAD_CONST                      58: ' \x1b[1;97m[+] Time :\x1b[1;92m '
                1212    LOAD_GLOBAL                     13: NULL + str
                1224    LOAD_FAST                       10: tim
                1226    PRECALL                         1
                1230    CALL                            1
                1240    BINARY_OP                       0 (+)
                1244    PRECALL                         1
                1248    CALL                            1
                1258    POP_TOP                         
                1260    LOAD_GLOBAL                     41: NULL + print
                1272    LOAD_CONST                      59: ' \x1b[1;97m[+] Date :\x1b[1;92m '
                1274    LOAD_FAST                       15: day
                1276    BINARY_OP                       0 (+)
                1280    LOAD_CONST                      60: '/'
                1282    BINARY_OP                       0 (+)
                1286    LOAD_FAST                       14: month
                1288    BINARY_OP                       0 (+)
                1292    LOAD_CONST                      60: '/'
                1294    BINARY_OP                       0 (+)
                1298    LOAD_FAST                       13: year
                1300    BINARY_OP                       0 (+)
                1304    PRECALL                         1
                1308    CALL                            1
                1318    POP_TOP                         
                1320    LOAD_GLOBAL                     41: NULL + print
                1332    LOAD_CONST                      61: ' \x1b[1;97m[+] Haterz : \x1b[1;92m'
                1334    LOAD_FAST                       4: hater
                1336    BINARY_OP                       0 (+)
                1340    PRECALL                         1
                1344    CALL                            1
                1354    POP_TOP                         
                1356    LOAD_GLOBAL                     41: NULL + print
                1368    LOAD_CONST                      62: ' \x1b[1;97m[+] Message :\x1b[1;92m '
                1370    LOAD_FAST                       4: hater
                1372    BINARY_OP                       0 (+)
                1376    LOAD_FAST                       6: msgs
                1378    BINARY_OP                       0 (+)
                1382    LOAD_CONST                      63: '\x1b[1;97m'
                1384    BINARY_OP                       0 (+)
                1388    PRECALL                         1
                1392    CALL                            1
                1402    POP_TOP                         
                1404    LOAD_GLOBAL                     41: NULL + print
                1416    LOAD_CONST                      64: '-------------------------------------------'
                1418    PRECALL                         1
                1422    CALL                            1
                1432    POP_TOP                         
                1434    JUMP_BACKWARD                   696 (to 46)
                1438    PUSH_EXC_INFO                   
                1440    LOAD_GLOBAL                     0: requests
                1452    LOAD_ATTR                       21: exceptions
                1462    LOAD_ATTR                       22: ConnectionError
                1472    CHECK_EXC_MATCH                 
                1474    POP_JUMP_FORWARD_IF_FALSE       24 (to 1524)
                1476    POP_TOP                         
                1478    LOAD_GLOBAL                     5: NULL + time
                1490    LOAD_ATTR                       3: sleep
                1500    LOAD_CONST                      65: 10
                1502    PRECALL                         1
                1506    CALL                            1
                1516    POP_TOP                         
                1518    POP_EXCEPT                      
                1520    JUMP_BACKWARD                   739 (to 46)
                1524    LOAD_GLOBAL                     46: Exception
                1536    CHECK_EXC_MATCH                 
                1538    POP_JUMP_FORWARD_IF_FALSE       11 (to 1562)
                1540    STORE_FAST                      29: e
                1542    POP_EXCEPT                      
                1544    LOAD_CONST                      0: None
                1546    STORE_FAST                      29: e
                1548    DELETE_FAST                     29: e
                1550    JUMP_BACKWARD                   754 (to 46)
                1554    LOAD_CONST                      0: None
                1556    STORE_FAST                      29: e
                1558    DELETE_FAST                     29: e
                1560    RERAISE                         1
                1562    RERAISE                         0
                1564    COPY                            3
                1566    POP_EXCEPT                      
                1568    RERAISE                         1
                1570    LOAD_FAST                       30: loop
                1572    LOAD_CONST                      40: 1
                1574    BINARY_OP                       13 (+=)
                1578    STORE_FAST                      30: loop
                1580    LOAD_CONST                      0: None
                1582    RETURN_VALUE                    
                1584    PUSH_EXC_INFO                   
                1586    LOAD_GLOBAL                     0: requests
                1598    LOAD_ATTR                       21: exceptions
                1608    LOAD_ATTR                       22: ConnectionError
                1618    CHECK_EXC_MATCH                 
                1620    POP_JUMP_FORWARD_IF_FALSE       24 (to 1670)
                1622    POP_TOP                         
                1624    LOAD_GLOBAL                     5: NULL + time
                1636    LOAD_ATTR                       3: sleep
                1646    LOAD_CONST                      65: 10
                1648    PRECALL                         1
                1652    CALL                            1
                1662    POP_TOP                         
                1664    POP_EXCEPT                      
                1666    LOAD_CONST                      0: None
                1668    RETURN_VALUE                    
                1670    LOAD_GLOBAL                     46: Exception
                1682    CHECK_EXC_MATCH                 
                1684    POP_JUMP_FORWARD_IF_FALSE       26 (to 1738)
                1686    STORE_FAST                      29: e
                1688    LOAD_GLOBAL                     41: NULL + print
                1700    LOAD_FAST                       29: e
                1702    PRECALL                         1
                1706    CALL                            1
                1716    POP_TOP                         
                1718    POP_EXCEPT                      
                1720    LOAD_CONST                      0: None
                1722    STORE_FAST                      29: e
                1724    DELETE_FAST                     29: e
                1726    LOAD_CONST                      0: None
                1728    RETURN_VALUE                    
                1730    LOAD_CONST                      0: None
                1732    STORE_FAST                      29: e
                1734    DELETE_FAST                     29: e
                1736    RERAISE                         1
                1738    RERAISE                         0
                1740    COPY                            3
                1742    POP_EXCEPT                      
                1744    RERAISE                         1
        [Code]
            File Name: dg
            Object Name: cpy
            Qualified Name: cpy
            Arg Count: 2
            Pos Only Arg Count: 0
            KW Only Arg Count: 0
            Stack Size: 5
            Flags: 0x00000003 (CO_OPTIMIZED | CO_NEWLOCALS)
            [Names]
                'range'
                'open'
                'write'
            [Locals+Names]
                'fileee'
                'lim'
                'i'
            [Constants]
                None
                'filer.txt'
                'a'
                '\n'
            [Disassembly]
                0       RESUME                          0
                2       LOAD_GLOBAL                     1: NULL + range
                14      LOAD_FAST                       1: lim
                16      PRECALL                         1
                20      CALL                            1
                30      GET_ITER                        
                32      FOR_ITER                        40 (to 114)
                34      STORE_FAST                      2: i
                36      LOAD_GLOBAL                     3: NULL + open
                48      LOAD_CONST                      1: 'filer.txt'
                50      LOAD_CONST                      2: 'a'
                52      PRECALL                         2
                56      CALL                            2
                66      LOAD_METHOD                     2: write
                88      LOAD_FAST                       0: fileee
                90      LOAD_CONST                      3: '\n'
                92      BINARY_OP                       0 (+)
                96      PRECALL                         1
                100     CALL                            1
                110     POP_TOP                         
                112     JUMP_BACKWARD                   41 (to 32)
                114     LOAD_CONST                      0: None
                116     RETURN_VALUE                    
    [Disassembly]
        0       RESUME                          0
        2       LOAD_CONST                      0: 0
        4       LOAD_CONST                      1: None
        6       IMPORT_NAME                     0: os
        8       STORE_NAME                      0: os
        10      LOAD_CONST                      0: 0
        12      LOAD_CONST                      1: None
        14      IMPORT_NAME                     1: sys
        16      STORE_NAME                      1: sys
        18      LOAD_CONST                      0: 0
        20      LOAD_CONST                      1: None
        22      IMPORT_NAME                     2: requests
        24      STORE_NAME                      2: requests
        26      LOAD_CONST                      0: 0
        28      LOAD_CONST                      1: None
        30      IMPORT_NAME                     3: re
        32      STORE_NAME                      3: re
        34      LOAD_CONST                      0: 0
        36      LOAD_CONST                      1: None
        38      IMPORT_NAME                     4: random
        40      STORE_NAME                      4: random
        42      LOAD_CONST                      0: 0
        44      LOAD_CONST                      1: None
        46      IMPORT_NAME                     5: time
        48      STORE_NAME                      5: time
        50      LOAD_CONST                      0: 0
        52      LOAD_CONST                      1: None
        54      IMPORT_NAME                     6: datetime
        56      STORE_NAME                      6: datetime
        58      LOAD_CONST                      0: 0
        60      LOAD_CONST                      1: None
        62      IMPORT_NAME                     7: getpass
        64      STORE_NAME                      7: getpass
        66      LOAD_CONST                      0: 0
        68      LOAD_CONST                      2: ('system',)
        70      IMPORT_NAME                     0: os
        72      IMPORT_FROM                     8: system
        74      STORE_NAME                      9: psl
        76      POP_TOP                         
        78      LOAD_CONST                      0: 0
        80      LOAD_CONST                      3: ('BeautifulSoup',)
        82      IMPORT_NAME                     10: bs4
        84      IMPORT_FROM                     11: BeautifulSoup
        86      STORE_NAME                      12: sop
        88      POP_TOP                         
        90      LOAD_CONST                      0: 0
        92      LOAD_CONST                      4: ('ThreadPoolExecutor',)
        94      IMPORT_NAME                     13: concurrent.futures
        96      IMPORT_FROM                     14: ThreadPoolExecutor
        98      STORE_NAME                      15: bsn
        100     POP_TOP                         
        102     PUSH_NULL                       
        104     LOAD_NAME                       9: psl
        106     LOAD_CONST                      5: 'rm -rf filer.txt'
        108     PRECALL                         1
        112     CALL                            1
        122     POP_TOP                         
        124     BUILD_LIST                      0
        126     STORE_NAME                      16: idd
        128     LOAD_CONST                      6: <CODE> logo
        130     MAKE_FUNCTION                   0
        132     STORE_NAME                      17: logo
        134     PUSH_NULL                       
        136     LOAD_NAME                       9: psl
        138     LOAD_CONST                      5: 'rm -rf filer.txt'
        140     PRECALL                         1
        144     CALL                            1
        154     POP_TOP                         
        156     BUILD_LIST                      0
        158     STORE_NAME                      16: idd
        160     LOAD_CONST                      7: <CODE> main
        162     MAKE_FUNCTION                   0
        164     STORE_NAME                      18: main
        166     LOAD_CONST                      8: <CODE> msg
        168     MAKE_FUNCTION                   0
        170     STORE_NAME                      19: msg
        172     LOAD_CONST                      9: <CODE> cpy
        174     MAKE_FUNCTION                   0
        176     STORE_NAME                      20: cpy
        178     PUSH_NULL                       
        180     LOAD_NAME                       18: main
        182     PRECALL                         0
        186     CALL                            0
        196     POP_TOP                         
        198     LOAD_CONST                      1: None
        200     RETURN_VALUE                    
